ipq/__init__.py
ipq/__main__.py
ipq/cli.py
ipq/errors.py
ipq/models.py
ipq/utils.py
ipq-0.2.1.dist-info/entry_points.txt
ipq-0.2.1.dist-info/LICENSE
ipq-0.2.1.dist-info/WHEEL
ipq-0.2.1.dist-info/METADATA
ipq-0.2.1.dist-info/RECORD
